vpc_cli/__init__.py
vpc_cli/command.py
vpc_cli/create_yaml.py
vpc_cli/deploy_cfn.py
vpc_cli/main.py
vpc_cli/print_table.py
vpc_cli/tools.py
vpc_cli/validators.py
aws_vpc_cli-0.5.7.dist-info/LICENSE
aws_vpc_cli-0.5.7.dist-info/METADATA
aws_vpc_cli-0.5.7.dist-info/WHEEL
aws_vpc_cli-0.5.7.dist-info/entry_points.txt
aws_vpc_cli-0.5.7.dist-info/top_level.txt
aws_vpc_cli-0.5.7.dist-info/RECORD
