Metadata-Version: 2.1
Name: aws-vpc-cli
Version: 0.5.7
Summary: AWS VPC CloudFormation Stack Generator
Home-page: https://github.com/marcus16-kang/vpc-stack-generator-cli
Author: marcus16-kang
Author-email: marcus16-kang@outlook.com
License: MIT
Project-URL: Source, https://github.com/marcus16-kang/vpc-stack-generator-cli
Requires-Python: >=3.8
License-File: LICENSE
Requires-Dist: ansicon (>=1.89.0)
Requires-Dist: aws-cloudformation-visualizer (>=0.0.3)
Requires-Dist: blessed (>=1.20.0)
Requires-Dist: boto3 (>=1.26.81)
Requires-Dist: botocore (>=1.29.81)
Requires-Dist: inquirer (>=3.1.2)
Requires-Dist: ipaddr (>=2.2.0)
Requires-Dist: jinxed (>=1.2.0)
Requires-Dist: jmespath (>=1.0.1)
Requires-Dist: prettytable (>=3.6.0)
Requires-Dist: pyfiglet (>=0.8.post1)
Requires-Dist: python-dateutil (>=2.8.2)
Requires-Dist: python-editor (>=1.0.4)
Requires-Dist: PyYAML (>=6.0)
Requires-Dist: readchar (==4.0.5)
Requires-Dist: s3transfer (>=0.6.0)
Requires-Dist: six (>=1.16.0)
Requires-Dist: urllib3 (>=1.26.14)
Requires-Dist: wcwidth (>=0.2.6)
